{"is_source_file": true, "format": "JavaScript (React JSX)", "description": "React component for a notification banner app, including form handling, toast notifications, and UI logic.", "external_files": ["./components/Toast", "./App.css", "./index.css"], "external_methods": ["setTimeout"], "published": ["App"], "classes": [], "methods": [{"name": "triggerToast", "description": "Shows a toast message of specified type, resetting its timer."}, {"name": "handleSubmit", "description": "Handles form submission, validates fields, and shows appropriate toast."}, {"name": "handleSaveChanges", "description": "Handles save changes button click, shows success toast."}, {"name": "App()", "scope": "", "scopeKind": "", "description": "unavailable"}], "calls": ["setToastMsg", "setToastType", "setShowToast", "setTimeout", "triggerToast", "handleSubmit", "handleSaveChanges", "setShowToast"], "search-terms": ["React App with toast notifications", "Form validation in React", "Toast component integration", "Notification banner React", "UI toast handling"], "state": 2, "file_id": 3, "knowledge_revision": 43, "git_revision": "1b610da8f9e414aed663ec7e04bac6ed899a2335", "revision_history": [{"19": "d3804298025baba76806ecf795165edae6fdc40e"}, {"34": "d3804298025baba76806ecf795165edae6fdc40e"}, {"40": "ca8ce73c7e5921d6179e0eec467d5af8f28f9385"}, {"41": "b9a0203d0f14bf3bee2bd80feb4d9f8177a7272f"}, {"43": "1b610da8f9e414aed663ec7e04bac6ed899a2335"}], "ctags": [{"_type": "tag", "name": "App", "path": "/home/kavia/workspace/code-generation/notification-banner-3295-3304/notification_frontend/src/App.js", "pattern": "/^function App() {$/", "language": "JavaScript", "kind": "function", "signature": "()"}, {"_type": "tag", "name": "handleSaveChanges", "path": "/home/kavia/workspace/code-generation/notification-banner-3295-3304/notification_frontend/src/App.js", "pattern": "/^                onClick={handleSaveChanges}$/", "language": "JavaScript", "kind": "field", "scope": "App.onClick", "scopeKind": "class"}, {"_type": "tag", "name": "password", "path": "/home/kavia/workspace/code-generation/notification-banner-3295-3304/notification_frontend/src/App.js", "pattern": "/^                  value={password}$/", "language": "JavaScript", "kind": "field", "scope": "App.value", "scopeKind": "class"}, {"_type": "tag", "name": "username", "path": "/home/kavia/workspace/code-generation/notification-banner-3295-3304/notification_frontend/src/App.js", "pattern": "/^                  value={username}$/", "language": "JavaScript", "kind": "field", "scope": "App.value", "scopeKind": "class"}], "hash": "c933bafda5971f21fdaa611171e229d8", "format-version": 4, "code-base-name": "notification_frontend", "filename": "notification_frontend/src/App.js", "fields": [{"name": "onClick={handleSaveChanges}", "scope": "App.onClick", "scopeKind": "class", "description": "unavailable"}, {"name": "value={password}", "scope": "App.value", "scopeKind": "class", "description": "unavailable"}, {"name": "value={username}", "scope": "App.value", "scopeKind": "class", "description": "unavailable"}]}